{
  "project_info": {
    "project_number": "215365428442",
    "project_id": "groovy-scarab-294501",
    "storage_bucket": "groovy-scarab-294501.appspot.com"
  },
  "client": [
    {
      "client_info": {
        "mobilesdk_app_id": "1:215365428442:android:322d42234d4a99f613f1e3",
        "android_client_info": {
          "package_name": "com.quick.asthkt"
        }
      },
      "oauth_client": [
        {
          "client_id": "215365428442-j7lupjlg2hfojel4k7u27djfifctqscr.apps.googleusercontent.com",
          "client_type": 3
        }
      ],
      "api_key": [
        {
          "current_key": "AIzaSyDZbEklsie1DPOqRaBVsdOIieLgDE6RHso"
        }
      ],
      "services": {
        "appinvite_service": {
          "other_platform_oauth_client": [
            {
              "client_id": "215365428442-j7lupjlg2hfojel4k7u27djfifctqscr.apps.googleusercontent.com",
              "client_type": 3
            }
          ]
        }
      }
    }
  ],
  "configuration_version": "1"
}